odoo9_addon_account_invoice_rounding-9.0.1.0.1.99.dev9-py2.7-nspkg.pth
odoo9_addon_account_invoice_rounding-9.0.1.0.1.99.dev9.dist-info/METADATA
odoo9_addon_account_invoice_rounding-9.0.1.0.1.99.dev9.dist-info/RECORD
odoo9_addon_account_invoice_rounding-9.0.1.0.1.99.dev9.dist-info/WHEEL
odoo9_addon_account_invoice_rounding-9.0.1.0.1.99.dev9.dist-info/namespace_packages.txt
odoo9_addon_account_invoice_rounding-9.0.1.0.1.99.dev9.dist-info/top_level.txt
odoo_addons/account_invoice_rounding/README.rst
odoo_addons/account_invoice_rounding/__init__.py
odoo_addons/account_invoice_rounding/__openerp__.py
odoo_addons/account_invoice_rounding/documentation/DOC_l10n_ch_5cts_roundings.ods
odoo_addons/account_invoice_rounding/i18n/account_invoice_rounding.pot
odoo_addons/account_invoice_rounding/i18n/am.po
odoo_addons/account_invoice_rounding/i18n/ar.po
odoo_addons/account_invoice_rounding/i18n/bg.po
odoo_addons/account_invoice_rounding/i18n/bs.po
odoo_addons/account_invoice_rounding/i18n/ca.po
odoo_addons/account_invoice_rounding/i18n/cs.po
odoo_addons/account_invoice_rounding/i18n/da.po
odoo_addons/account_invoice_rounding/i18n/de.po
odoo_addons/account_invoice_rounding/i18n/el_GR.po
odoo_addons/account_invoice_rounding/i18n/en_GB.po
odoo_addons/account_invoice_rounding/i18n/es.po
odoo_addons/account_invoice_rounding/i18n/es_CR.po
odoo_addons/account_invoice_rounding/i18n/es_EC.po
odoo_addons/account_invoice_rounding/i18n/es_ES.po
odoo_addons/account_invoice_rounding/i18n/es_MX.po
odoo_addons/account_invoice_rounding/i18n/es_PE.po
odoo_addons/account_invoice_rounding/i18n/et.po
odoo_addons/account_invoice_rounding/i18n/eu.po
odoo_addons/account_invoice_rounding/i18n/fi.po
odoo_addons/account_invoice_rounding/i18n/fr.po
odoo_addons/account_invoice_rounding/i18n/fr_CA.po
odoo_addons/account_invoice_rounding/i18n/fr_CH.po
odoo_addons/account_invoice_rounding/i18n/fr_FR.po
odoo_addons/account_invoice_rounding/i18n/gl.po
odoo_addons/account_invoice_rounding/i18n/hr.po
odoo_addons/account_invoice_rounding/i18n/hr_HR.po
odoo_addons/account_invoice_rounding/i18n/hu.po
odoo_addons/account_invoice_rounding/i18n/id.po
odoo_addons/account_invoice_rounding/i18n/it.po
odoo_addons/account_invoice_rounding/i18n/ja.po
odoo_addons/account_invoice_rounding/i18n/lt.po
odoo_addons/account_invoice_rounding/i18n/mk.po
